[
    {
        "id":"5ece4797eaf5e",
        "cover":"https://images.unsplash.com/photo-1580757468214-c73f7062a5cb?ixlib=rb-4.0.3&ixid=M3wxMjA3fDB8MHxwaG90by1wYWdlfHx8fGVufDB8fHx8fA%3D%3D&auto=format&fit=crop&w=1932&q=80",
        "profilePic":"https://images.unsplash.com/photo-1539571696357-5a69c17a67c6?ixlib=rb-4.0.3&ixid=M3wxMjA3fDB8MHxwaG90by1wYWdlfHx8fGVufDB8fHx8fA%3D%3D&auto=format&fit=crop&w=1887&q=80",
        "name":"Connor Lewis",
        "date":"7/10/2023",
        "title":"Animated Glass Morphism Product Card HTML CSS",
        "hashtags":["html","css", "js"],
        "readingTime":7
    },
    {
        "id":"64f19fea2cbcc",
        "cover":"https://images.unsplash.com/photo-1558637845-c8b7ead71a3e?ixlib=rb-4.0.3&ixid=M3wxMjA3fDB8MHxwaG90by1wYWdlfHx8fGVufDB8fHx8fA%3D%3D&auto=format&fit=crop&w=1932&q=80",
        "profilePic":"https://images.unsplash.com/photo-1530268729831-4b0b9e170218?ixlib=rb-4.0.3&ixid=M3wxMjA3fDB8MHxwaG90by1wYWdlfHx8fGVufDB8fHx8fA%3D%3D&auto=format&fit=crop&w=2070&q=80",
        "name":"Jake Ward",
        "date":"7/14/2023",
        "title":"Create Responsive Navigation Menu Bar Using HTML CSS",
        "hashtags":["html","webdev", "css", "javascript"],
        "readingTime":10
    },
    {
        "id":"64f1a06648b14",
        "cover":"https://images.unsplash.com/photo-1599454100789-b211e369bd04?ixlib=rb-4.0.3&ixid=M3wxMjA3fDB8MHxwaG90by1wYWdlfHx8fGVufDB8fHx8fA%3D%3D&auto=format&fit=crop&w=1906&q=80",
        "profilePic":"https://images.unsplash.com/photo-1472099645785-5658abf4ff4e?ixlib=rb-4.0.3&ixid=M3wxMjA3fDB8MHxwaG90by1wYWdlfHx8fGVufDB8fHx8fA%3D%3D&auto=format&fit=crop&w=2070&q=80",
        "name":"Harry Miller",
        "date":"7/22/2023",
        "title":"300+ React Interview Questions",
        "hashtags":["react","js", "interview", "beginner"],
        "readingTime":30

    },
    {
        "id":"64f1a06648b53",
        "cover":"https://images.unsplash.com/photo-1594568284297-7c64464062b1?ixlib=rb-4.0.3&ixid=M3wxMjA3fDB8MHxwaG90by1wYWdlfHx8fGVufDB8fHx8fA%3D%3D&auto=format&fit=crop&w=2070&q=80",
        "profilePic":"https://images.unsplash.com/photo-1501196354995-cbb51c65aaea?ixlib=rb-4.0.3&ixid=M3wxMjA3fDB8MHxwaG90by1wYWdlfHx8fGVufDB8fHx8fA%3D%3D&auto=format&fit=crop&w=2071&q=80",
        "name":"Nate Collins",
        "date":"5/10/2023",
        "title":"Awesome Things Related To React Hooks",
        "hashtags":["react","hooks", "beginner"],
        "readingTime":12
    },
    {
        "id":"64f1a06648b8f",
        "cover":"https://images.unsplash.com/photo-1626593261859-4fe4865d8cb1?ixlib=rb-4.0.3&ixid=M3wxMjA3fDB8MHxwaG90by1wYWdlfHx8fGVufDB8fHx8fA%3D%3D&auto=format&fit=crop&w=2070&q=80",
        "profilePic":"https://images.unsplash.com/photo-1496345875659-11f7dd282d1d?ixlib=rb-4.0.3&ixid=M3wxMjA3fDB8MHxwaG90by1wYWdlfHx8fGVufDB8fHx8fA%3D%3D&auto=format&fit=crop&w=2070&q=80",
        "name":"Matthew Walker",
        "date":"6/22/2023",
        "title":"Bootstrap 5 Toasts",
        "hashtags":["bootstrap","styling"],
        "readingTime":15

    },
    {
        "id":"64f1a06648bcb",
        "cover":"https://images.unsplash.com/photo-1595835018349-198460e1d309?ixlib=rb-4.0.3&ixid=M3wxMjA3fDB8MHxwaG90by1wYWdlfHx8fGVufDB8fHx8fA%3D%3D&auto=format&fit=crop&w=1931&q=80",
        "profilePic":"https://images.unsplash.com/photo-1521119989659-a83eee488004?ixlib=rb-4.0.3&ixid=M3wxMjA3fDB8MHxwaG90by1wYWdlfHx8fGVufDB8fHx8fA%3D%3D&auto=format&fit=crop&w=1923&q=80",
        "name":"Ashton Wright",
        "date":"6/21/2023",
        "title":"Basic unit testing in Haskell using HUnit and Cabal",
        "hashtags":["haskell","tdd"],
        "readingTime":7
    },
    {
        "id":"64f1a06648c06",
        "cover":"https://images.unsplash.com/photo-1495443396064-16fd983acb6a?ixlib=rb-4.0.3&ixid=M3wxMjA3fDB8MHxwaG90by1wYWdlfHx8fGVufDB8fHx8fA%3D%3D&auto=format&fit=crop&w=1932&q=80",
        "profilePic":"https://images.unsplash.com/photo-1488161628813-04466f872be2?ixlib=rb-4.0.3&ixid=M3wxMjA3fDB8MHxwaG90by1wYWdlfHx8fGVufDB8fHx8fA%3D%3D&auto=format&fit=crop&w=1964&q=80",
        "name":"Finn Smith",
        "date":"5/22/2023",
        "title":"Best Websites Every Programmer Should Visit",
        "hashtags":["showdev","programming", "programmer", "tips"],
        "readingTime":9
    }
]